matrioska/__main__.py
matrioska/argparser.py
matrioska/encryption.py
matrioska/file.py
matrioska/key.py
matrioska/version.py
tests/test_version.py
matrioska-0.0.1.dist-info/LICENSE
matrioska-0.0.1.dist-info/METADATA
matrioska-0.0.1.dist-info/WHEEL
matrioska-0.0.1.dist-info/entry_points.txt
matrioska-0.0.1.dist-info/top_level.txt
matrioska-0.0.1.dist-info/RECORD
