Metadata-Version: 2.1
Name: matrioska
Version: 0.0.1
Summary: Command line tool and Python library for data encryption
Home-page: https://github.com/joaompinto/matrioska
Author: João Pinto
Author-email: lamego.pinto@gmail.com
License: MIT
Platform: UNKNOWN
License-File: LICENSE
Requires-Dist: pycryptodomex
